project_context_mcp/__init__.py
project_context_mcp/server.py
project_context_mcp-1.0.0.dist-info/METADATA
project_context_mcp-1.0.0.dist-info/WHEEL
project_context_mcp-1.0.0.dist-info/entry_points.txt
project_context_mcp-1.0.0.dist-info/licenses/LICENSE
project_context_mcp-1.0.0.dist-info/RECORD
