Metadata-Version: 2.4
Name: project-context-mcp
Version: 1.0.0
Summary: MCP server that exposes .context/ folder files as resources in Claude Code
Author-email: Eric Brown <eric@ericbrown.com>
License: MIT
License-File: LICENSE
Keywords: claude,claude-code,context,documentation,mcp
Classifier: Development Status :: 4 - Beta
Classifier: Intended Audience :: Developers
Classifier: License :: OSI Approved :: MIT License
Classifier: Programming Language :: Python :: 3
Classifier: Programming Language :: Python :: 3.10
Classifier: Programming Language :: Python :: 3.11
Classifier: Programming Language :: Python :: 3.12
Requires-Python: >=3.10
Requires-Dist: mcp>=1.0.0
